globmatch/__init__.py
globmatch/_version.py
globmatch/pathutils.py
globmatch/translation.py
globmatch-2.0.0.dist-info/LICENSE.md
globmatch-2.0.0.dist-info/METADATA
globmatch-2.0.0.dist-info/WHEEL
globmatch-2.0.0.dist-info/pbr.json
globmatch-2.0.0.dist-info/top_level.txt
globmatch-2.0.0.dist-info/RECORD
